OmMariamFlow/Activations.py
OmMariamFlow/Data.py
OmMariamFlow/Function.py
OmMariamFlow/Layers.py
OmMariamFlow/Losses.py
OmMariamFlow/Model.py
OmMariamFlow/OmMariamFlow.py
OmMariamFlow/Optimizations.py
OmMariamFlow/Test_Q8_Sheet4.py
OmMariamFlow/Utils.py
OmMariamFlow/Visualizer.py
OmMariamFlow/__init__.py
OmMariamFlow-0.0.9.dist-info/LICENSE.txt
OmMariamFlow-0.0.9.dist-info/METADATA
OmMariamFlow-0.0.9.dist-info/WHEEL
OmMariamFlow-0.0.9.dist-info/top_level.txt
OmMariamFlow-0.0.9.dist-info/RECORD
